openpii_vault/__init__.py
openpii_vault/canonicalizers.py
openpii_vault/json_path_utils.py
openpii_vault/salt_provider.py
openpii_vault/spark_udf.py
openpii_vault/tokenization.py
openpii_vault/tokenize_cdc_df.py
openpii_vault/vault_utils.py
openpii_vault-0.1.0.dist-info/licenses/LICENSE
openpii_vault-0.1.0.dist-info/METADATA
openpii_vault-0.1.0.dist-info/WHEEL
openpii_vault-0.1.0.dist-info/top_level.txt
openpii_vault-0.1.0.dist-info/RECORD
