Metadata-Version: 2.4
Name: openpii-vault
Version: 0.1.0
Summary: Format-/structure-preserving tokenization for JSON payloads (Spark/Glue friendly).
Author-email: Shobha Sethuraman <shobha.sethuraman@gmail.com>
License: Copyright (c) 2025 Shobha Sethuraman
Project-URL: Homepage, https://github.com/logicoflife/openpii-vault
Project-URL: Repository, https://github.com/logicoflife/openpii-vault
Project-URL: Issues, https://github.com/logicoflife/openpii-vault/issues
Keywords: pii,tokenization,privacy,json,spark,glue
Classifier: Development Status :: 3 - Alpha
Classifier: License :: OSI Approved :: Apache Software License
Classifier: Programming Language :: Python :: 3
Classifier: Programming Language :: Python :: 3 :: Only
Classifier: Programming Language :: Python :: 3.9
Classifier: Programming Language :: Python :: 3.10
Classifier: Programming Language :: Python :: 3.11
Classifier: Intended Audience :: Developers
Classifier: Topic :: Security :: Cryptography
Classifier: Topic :: Software Development :: Libraries :: Python Modules
Requires-Python: >=3.9
License-File: LICENSE
Provides-Extra: spark
Requires-Dist: pyspark>=3.3; extra == "spark"
Dynamic: license-file
